{
  "type": "forge:conditional",
  "recipes": [
    {
      "conditions": [
        {
          "type": "forge:mod_loaded",
          "modid": "minecraft"
        }
      ],
      "recipe": {
        "type": "minecraft:crafting_shaped",
        "group": "morestoragedrawers",
        "key": {
          "/": {
            "item": "minecraft:terracotta"
          },
          "x": {
            "tag": "forge:chests/wooden"
          }
        },
        "pattern": [
          "///",
          " x ",
          "///"
        ],
        "result": {
          "item": "morestoragedrawers:minecraft_terracotta_full_1"
        }
      }
    }
  ]
}