{
  "type": "forge:conditional",
  "recipes": [
    {
      "conditions": [
        {
          "type": "forge:mod_loaded",
          "modid": "minecraft"
        }
      ],
      "recipe": {
        "type": "minecraft:crafting_shaped",
        "category": "misc",
        "group": "morestoragedrawers",
        "key": {
          "/": {
            "item": "minecraft:brown_terracotta"
          },
          "x": {
            "tag": "forge:chests/wooden"
          }
        },
        "pattern": [
          "x/x",
          "///",
          "x/x"
        ],
        "result": {
          "count": 4,
          "item": "morestoragedrawers:minecraft_brown_terracotta_full_4"
        },
        "show_notification": true
      }
    }
  ]
}